myfunctions_dorukkakici/__init__.py
myfunctions_dorukkakici/math.py
myfunctions_dorukkakici-0.0.1.dist-info/METADATA
myfunctions_dorukkakici-0.0.1.dist-info/WHEEL
myfunctions_dorukkakici-0.0.1.dist-info/top_level.txt
myfunctions_dorukkakici-0.0.1.dist-info/RECORD
