Metadata-Version: 2.1
Name: myfunctions-dorukkakici
Version: 0.0.1
Summary: A description of your package
Home-page: https://github.com/dorukkakici/
Author: Doruk Kakici
Author-email: kakicidoruk@gmail.com
License: MIT
Platform: UNKNOWN
Classifier: Programming Language :: Python :: 3
Classifier: License :: OSI Approved :: MIT License
Classifier: Operating System :: OS Independent
Requires-Python: >=3.6
